plenty_taxhub_generator/__init__.py
plenty_taxhub_generator/__main__.py
plenty_taxhub_generator/cli.py
plenty_taxhub_generator/packages/taxhub.py
plenty_taxhub_generator/packages/utils.py
plenty_taxhub_generator-0.0.4.dist-info/LICENSE
plenty_taxhub_generator-0.0.4.dist-info/WHEEL
plenty_taxhub_generator-0.0.4.dist-info/METADATA
plenty_taxhub_generator-0.0.4.dist-info/RECORD
