Metadata-Version: 2.1
Name: plenty-taxhub-generator
Version: 0.0.4
Summary: Generate the required data sheet for the DutyPay(dutypay.eu) TaxHub platform from Plentymarkets.
License: MIT
Author: Sebastian Fricke
Author-email: sebastian.fricke.linux@gmail.com
Requires-Python: >=3.7,<4.0
Classifier: License :: OSI Approved :: MIT License
Classifier: Programming Language :: Python :: 3
Classifier: Programming Language :: Python :: 3.7
Classifier: Programming Language :: Python :: 3.8
Classifier: Programming Language :: Python :: 3.9
Requires-Dist: loguru (>=0.5.3,<0.6.0)
Requires-Dist: plenty_api (>=0.2,<0.3)
Requires-Dist: pylint (>=2.6.0,<3.0.0)
Requires-Dist: requests (>=2.24.0,<3.0.0)
Requires-Dist: typing (>=3.7.4,<4.0.0)
